PaDEL_pywrapper/__init__.py
PaDEL_pywrapper/descriptor.py
PaDEL_pywrapper/padel_descs.tsv
PaDEL_pywrapper/padel_fps.tsv
PaDEL_pywrapper/padel_wrapper.py
PaDEL_pywrapper/utils.py
PaDEL_pywrapper/PaDEL-Descriptor/Descriptors.xls
PaDEL_pywrapper/PaDEL-Descriptor/PaDEL-Descriptor.jar
PaDEL_pywrapper/PaDEL-Descriptor/descriptors.xml
PaDEL_pywrapper/PaDEL-Descriptor/lib/ambit2-base-2.4.7-SNAPSHOT.jar
PaDEL_pywrapper/PaDEL-Descriptor/lib/ambit2-core-2.4.7-SNAPSHOT.jar
PaDEL_pywrapper/PaDEL-Descriptor/lib/ambit2-smarts-2.4.7-SNAPSHOT.jar
PaDEL_pywrapper/PaDEL-Descriptor/lib/appframework-1.0.3.jar
PaDEL_pywrapper/PaDEL-Descriptor/lib/cdk-1.4.15.jar
PaDEL_pywrapper/PaDEL-Descriptor/lib/commons-cli-1.2.jar
PaDEL_pywrapper/PaDEL-Descriptor/lib/commons-cli-1.5.0.jar
PaDEL_pywrapper/PaDEL-Descriptor/lib/ePaDEL.jar
PaDEL_pywrapper/PaDEL-Descriptor/lib/elibPaDEL-Descriptor.jar
PaDEL_pywrapper/PaDEL-Descriptor/lib/guava-17.0.jar
PaDEL_pywrapper/PaDEL-Descriptor/lib/jama.jar
PaDEL_pywrapper/PaDEL-Descriptor/lib/jgrapht-0.6.0.jar
PaDEL_pywrapper/PaDEL-Descriptor/lib/l2fprod-common-all.jar
PaDEL_pywrapper/PaDEL-Descriptor/lib/libPaDEL-Descriptor.jar
PaDEL_pywrapper/PaDEL-Descriptor/lib/libPaDEL-Jobs.jar
PaDEL_pywrapper/PaDEL-Descriptor/lib/libPaDEL.jar
PaDEL_pywrapper/PaDEL-Descriptor/lib/swing-worker-1.1.jar
PaDEL_pywrapper/PaDEL-Descriptor/lib/vecmath1.2-1.14.jar
PaDEL_pywrapper/PaDEL-Descriptor/lib/xom-1.1.jar
PaDEL_pywrapper/PaDEL-Descriptor/license/LICENSE.txt
PaDEL_pywrapper/PaDEL-Descriptor/license/README - CDK
PaDEL_pywrapper/PaDEL-Descriptor/license/lgpl-2.1.txt
PaDEL_pywrapper/PaDEL-Descriptor/license/lgpl.license
padel_pywrapper-1.0.6.dist-info/licenses/LICENSE
padel_pywrapper-1.0.6.dist-info/METADATA
padel_pywrapper-1.0.6.dist-info/WHEEL
padel_pywrapper-1.0.6.dist-info/top_level.txt
padel_pywrapper-1.0.6.dist-info/RECORD
